scriptx/__init__.py
scriptx/_version.py
scriptx/main.py
scriptx/py.typed
scriptx-0.1.6.dist-info/METADATA
scriptx-0.1.6.dist-info/WHEEL
scriptx-0.1.6.dist-info/entry_points.txt
scriptx-0.1.6.dist-info/licenses/LICENSE.txt
scriptx-0.1.6.dist-info/RECORD
