Metadata-Version: 2.4
Name: scriptx
Version: 0.1.6
Summary: A lightweight manager for PEP 723 Python scripts - install, run, update, and manage standalone scripts with isolated environments.
Project-URL: Documentation, https://github.com/FlavioAmurrioCS/scriptx#readme
Project-URL: Issues, https://github.com/FlavioAmurrioCS/scriptx/issues
Project-URL: Source, https://github.com/FlavioAmurrioCS/scriptx
Author-email: Flavio Amurrio <25621374+FlavioAmurrioCS@users.noreply.github.com>
License-Expression: MIT
License-File: LICENSE.txt
Classifier: Development Status :: 4 - Beta
Classifier: Programming Language :: Python
Classifier: Programming Language :: Python :: 3.9
Classifier: Programming Language :: Python :: 3.10
Classifier: Programming Language :: Python :: 3.11
Classifier: Programming Language :: Python :: 3.12
Classifier: Programming Language :: Python :: 3.13
Classifier: Programming Language :: Python :: 3.14
Classifier: Programming Language :: Python :: Implementation :: CPython
Classifier: Programming Language :: Python :: Implementation :: PyPy
Requires-Python: >=3.9
Requires-Dist: packaging
Requires-Dist: tomli>=1.1.0; python_version < '3.11'
Requires-Dist: uv
